odoo8_addon_account_invoice_line_price_subtotal_gross-8.0.1.0.0.99.dev12-py2.7-nspkg.pth
odoo8_addon_account_invoice_line_price_subtotal_gross-8.0.1.0.0.99.dev12.dist-info/DESCRIPTION.rst
odoo8_addon_account_invoice_line_price_subtotal_gross-8.0.1.0.0.99.dev12.dist-info/METADATA
odoo8_addon_account_invoice_line_price_subtotal_gross-8.0.1.0.0.99.dev12.dist-info/RECORD
odoo8_addon_account_invoice_line_price_subtotal_gross-8.0.1.0.0.99.dev12.dist-info/WHEEL
odoo8_addon_account_invoice_line_price_subtotal_gross-8.0.1.0.0.99.dev12.dist-info/metadata.json
odoo8_addon_account_invoice_line_price_subtotal_gross-8.0.1.0.0.99.dev12.dist-info/namespace_packages.txt
odoo8_addon_account_invoice_line_price_subtotal_gross-8.0.1.0.0.99.dev12.dist-info/top_level.txt
odoo_addons/account_invoice_line_price_subtotal_gross/README.rst
odoo_addons/account_invoice_line_price_subtotal_gross/__init__.py
odoo_addons/account_invoice_line_price_subtotal_gross/__openerp__.py
odoo_addons/account_invoice_line_price_subtotal_gross/account.py
odoo_addons/account_invoice_line_price_subtotal_gross/account_view.xml
odoo_addons/account_invoice_line_price_subtotal_gross/i18n/account_invoice_line_price_subtotal_gross.pot
odoo_addons/account_invoice_line_price_subtotal_gross/i18n/bs.po
odoo_addons/account_invoice_line_price_subtotal_gross/i18n/ca.po
odoo_addons/account_invoice_line_price_subtotal_gross/i18n/cs.po
odoo_addons/account_invoice_line_price_subtotal_gross/i18n/de.po
odoo_addons/account_invoice_line_price_subtotal_gross/i18n/es.po
odoo_addons/account_invoice_line_price_subtotal_gross/i18n/es_MX.po
odoo_addons/account_invoice_line_price_subtotal_gross/i18n/fr.po
odoo_addons/account_invoice_line_price_subtotal_gross/i18n/fr_CH.po
odoo_addons/account_invoice_line_price_subtotal_gross/i18n/hr.po
odoo_addons/account_invoice_line_price_subtotal_gross/i18n/hr_HR.po
odoo_addons/account_invoice_line_price_subtotal_gross/i18n/it.po
odoo_addons/account_invoice_line_price_subtotal_gross/i18n/nl_BE.po
odoo_addons/account_invoice_line_price_subtotal_gross/i18n/nl_NL.po
odoo_addons/account_invoice_line_price_subtotal_gross/i18n/pt_BR.po
odoo_addons/account_invoice_line_price_subtotal_gross/i18n/pt_PT.po
odoo_addons/account_invoice_line_price_subtotal_gross/i18n/sl.po
odoo_addons/account_invoice_line_price_subtotal_gross/i18n/tr.po
odoo_addons/account_invoice_line_price_subtotal_gross/i18n/tr_TR.po
odoo_addons/account_invoice_line_price_subtotal_gross/static/description/icon.png
